{
	"action": {
		"message": "Ação",
		"description": "Table title in management page"
	},
	"add": {
		"message": "Adicionar",
		"description": "Button to add somethings"
	},
	"add_anti_hot_link": {
		"message": "Adicione uma regra de link anti-roubo",
		"description": "Right-click menu to add a rule"
	},
	"add_anti_hot_link_to_menu": {
		"message": "Adicione \"Adicionar link anti-roubo\" ao botão direito no menu",
		"description": "A option. if enabled, a menu item well add to the right-click menu, Hotlinking: https://en.wikipedia.org/wiki/Inline_linking"
	},
	"auto": {
		"message": "Auto",
		"description": "Auto detect dark mode"
	},
	"batch_delete": {
		"message": "eliminação do lote",
		"description": "Button to delete multiple rules"
	},
	"batch_mode": {
		"message": "Operação por lotes",
		"description": "Button to enter batch operation mode"
	},
	"cancel": {
		"message": "Cancelar",
		"description": "Button to close modal without save"
	},
	"choose": {
		"message": "Escolher",
		"description": "Choose a group"
	},
	"clone": {
		"message": "Clonar",
		"description": "Clone rule"
	},
	"cloud_backup": {
		"message": "Backup em nuvem",
		"description": "Cloud backup button"
	},
	"cloud_backup_at": {
		"message": "Último backup em $date$",
		"description": "Display last backup time if any backup found",
		"placeholders": {
			"date": {
				"content": "$1"
			}
		}
	},
	"cloud_no_backup": {
		"message": "Sem backup ",
		"description": "Display if no backup found"
	},
	"cloud_over_limit": {
		"message": "Limite do tamanho de backup excedido",
		"description": "Message display when exceeded backup size limit"
	},
	"code": {
		"message": "Código",
		"description": "Label for code section in modal"
	},
	"code_empty": {
		"message": "O código não pode estar vazio",
		"description": "Tips when a rule is custom function but code is empty"
	},
	"dark_mode": {
		"message": "Dark mode",
		"description": "Dark mode select"
	},
	"dark_mode_help": {
		"message": "Dark mode is experimental, refresh this page to see the effect",
		"description": "Dark help text"
	},
	"delete": {
		"message": "Apagar",
		"description": "Delete button"
	},
	"delete_confirm": {
		"message": "Deseja excluir estas regras?",
		"description": "A confirmation box shows when user want to delete rules"
	},
	"description": {
		"message": "Gerencie pedidos do navegador, incluindo modificar cabeçalhos das solicitações e resposta, solicitações de redirecionamento, cancelar solicitações",
		"description": "Extension description"
	},
	"disable": {
		"message": "Disable",
		"description": "disable"
	},
	"display_common_header": {
		"message": "Exibir cabeçalho comum",
		"description": "An option to enable header auto-complete when editing rules"
	},
	"download": {
		"message": "Download",
		"description": "Download button"
	},
	"download_rule": {
		"message": "Regra de download",
		"description": "Title of the rule download area"
	},
	"edit": {
		"message": "Editar",
		"description": "Modal title for editing a rule"
	},
	"enable": {
		"message": "Habilitar",
		"description": "Switch one rule on/off in table title"
	},
	"enable_he": {
		"message": "Ativar editor de cabeçalho",
		"description": "If not checked, all rules will take no effects"
	},
	"encoding": {
		"message": "Encoding",
		"description": "Label for responseBody's character encoding"
	},
	"enter_group_name": {
		"message": "Digite um nome de grupo",
		"description": "Prompt the user when the user click add group button"
	},
	"excludeRule": {
		"message": "Excluir regra",
		"description": "Label for exclude rule in modal"
	},
	"exec_function": {
		"message": "Função personalizada",
		"description": "Custom function in execute type"
	},
	"exec_normal": {
		"message": "normal",
		"description": "Normal option in execute type"
	},
	"exec_type": {
		"message": "Execute o tipo",
		"description": "Label for execute type in modal"
	},
	"export": {
		"message": "Exportar",
		"description": "Button to export all rules as a json file"
	},
	"export_and_import": {
		"message": "Exportar e Importar",
		"description": "The tab title in the top"
	},
	"extButtonTitle": {
		"message": "Header Editor",
		"description": "Toolbar tooltip"
	},
	"extName": {
		"message": "Header Editor",
		"description": "Extension name"
	},
	"group": {
		"message": "Grupo",
		"description": "Group button"
	},
	"headerName": {
		"message": "Nome do cabeçalho",
		"description": "Label for header name in modal"
	},
	"headerValue": {
		"message": "Valor do cabeçalho",
		"description": "Label for header value in modal"
	},
	"header_empty": {
		"message": "Nome do cabeçalho não pode estar vazio",
		"description": "Message for saving a rule without header name"
	},
	"help": {
		"message": "Ajuda",
		"description": "Help link"
	},
	"import": {
		"message": "Importar",
		"description": "Button to import rules from a file"
	},
	"import_drop": {
		"message": "Não importar",
		"description": "do not import a rule"
	},
	"import_new": {
		"message": "Adicionar",
		"description": "Add a new rule"
	},
	"import_override": {
		"message": "Substituições existentes",
		"description": "Overrides already existing rule"
	},
	"import_success": {
		"message": "Importado com sucesso",
		"description": "Displays when import successfully"
	},
	"include_header_in_custom_function": {
		"message": "Incluir cabeçalhos na função personalizada",
		"description": "An option to enable this feature, for more info, see wiki in GitHub"
	},
	"manage": {
		"message": "Gerir",
		"description": "Manage rules, options and more"
	},
	"manage_collapse_group": {
		"message": "Reduzir grupos por padrão",
		"description": "All groups will be collapsed when open the management page"
	},
	"matchRule": {
		"message": "Regras correspondentes",
		"description": "Label for match rule in modal"
	},
	"matchType": {
		"message": "Tipo de combinação",
		"description": "Label for match type in modal"
	},
	"match_all": {
		"message": "Todos",
		"description": "All option in modal"
	},
	"match_domain": {
		"message": "Domínio",
		"description": "Domain option in modal"
	},
	"match_prefix": {
		"message": "Prefixo da URL",
		"description": "URL prefix option in modal"
	},
	"match_regexp": {
		"message": "Expressão regular",
		"description": "Regular expression option in modal"
	},
	"match_rule_empty": {
		"message": "A regra  não pode estar vazia",
		"description": "Message for saving a rule without match rule"
	},
	"match_url": {
		"message": "URL",
		"description": "URL option in modal"
	},
	"modify_body": {
		"message": "Modify response body (only supports Firefox)",
		"description": "Option to enable/disable modify body"
	},
	"name": {
		"message": "Nome",
		"description": "Label for name in modal"
	},
	"name_empty": {
		"message": "Nome não pode estar vazio",
		"description": "Message for saving a rule without name"
	},
	"ok": {
		"message": "OK",
		"description": "OK Button"
	},
	"options": {
		"message": "Opções",
		"description": "Heading for options section on manage page."
	},
	"pack_up_or_unfurl": {
		"message": "Pacote acima ou desenrolar grupo",
		"description": "Button to pack up or unfurl a group"
	},
	"redirectTo": {
		"message": "Redirecionar para",
		"description": "Label for redirect to in modal"
	},
	"redirect_empty": {
		"message": "O alvo de redirecionamento não pode estar vazio",
		"description": "Message for saving a rule without redirect target if rule type is redirect"
	},
	"rename": {
		"message": "Renomear",
		"description": "Rename group"
	},
	"ruleType": {
		"message": "Tipo de regra",
		"description": "Label for rule type in modal"
	},
	"rule_cancel": {
		"message": "Cancelar pedido",
		"description": "Cancel request option in modal"
	},
	"rule_list": {
		"message": "Lista de regras",
		"description": "Title of the rules list"
	},
	"rule_modifyReceiveBody": {
		"message": "Modify response body",
		"description": "Response body option in modal"
	},
	"rule_modifyReceiveHeader": {
		"message": "Modificar o cabeçalho da resposta",
		"description": "Response header option in modal"
	},
	"rule_modifySendHeader": {
		"message": "Modificar o cabeçalho solicitado",
		"description": "Request header option in modal"
	},
	"rule_redirect": {
		"message": "Pedido de redirecionamento",
		"description": "Redirect option in modal"
	},
	"rules_no_effect_for_he": {
		"message": "Regras não têm efeito no Header Editor",
		"description": "If checked, all rules will take no effect on pages in Header Editor"
	},
	"save": {
		"message": "Salvar",
		"description": "Button to save a rule"
	},
	"save_to": {
		"message": "Salvar para",
		"description": "Save rule to"
	},
	"saved": {
		"message": "Salvo",
		"description": "Displays when rule saved successfully"
	},
	"select_all": {
		"message": "Selecionar/Desmarcar tudo",
		"description": "Button to select or unselect all rules in batch management mode"
	},
	"select_or_download": {
		"message": "Importe de um arquivo local ou regras de download",
		"description": "A notice in import card"
	},
	"share": {
		"message": "Compartilhar",
		"description": "Share button title"
	},
	"suggested_group": {
		"message": "Grupo sugerido",
		"description": "The suggested group name provided by the rule author"
	},
	"test_custom_code": {
		"message": "Não suporta testar código personalizado agora",
		"description": "Label to test a redirect rule"
	},
	"test_exclude": {
		"message": "Combinado, mas excluído",
		"description": "Label to test a redirect rule"
	},
	"test_invalid_regexp": {
		"message": "A expressão regular é inválida",
		"description": "Label to test a redirect rule"
	},
	"test_mismatch": {
		"message": "Incompatibilidade",
		"description": "Label to test a redirect rule"
	},
	"test_url": {
		"message": "Teste (Não será salvo)",
		"description": "Label to test a redirect rule"
	},
	"third_party_rules": {
		"message": "Regras de terceiros",
		"description": "Link to find more third party rules"
	},
	"ungrouped": {
		"message": "Desagrupado",
		"description": "The default group name"
	},
	"upload": {
		"message": "Upload",
		"description": "Upload button"
	},
	"url_cloud_backup": {
		"message": "https://he.firefoxcn.net/en/cloud-backup.html",
		"description": "URL of documentions, if not translated, please use english version"
	},
	"url_help": {
		"message": "https://he.firefoxcn.net/en/guide.html",
		"description": "URL of documentions, if not translated, please use english version"
	},
	"url_third_party_rules": {
		"message": "https://he.firefoxcn.net/en/third-party-rules.html",
		"description": "URL of documentions, if not translated, please use english version"
	},
	"view": {
		"message": "Visualizar",
		"description": "View rule or a link"
	}
}